AUTHORS.txt
CHANGELOG.txt
LICENSE.txt
README.txt
setup.py
coopr/__init__.py
coopr.data.cute.egg-info/PKG-INFO
coopr.data.cute.egg-info/SOURCES.txt
coopr.data.cute.egg-info/dependency_links.txt
coopr.data.cute.egg-info/namespace_packages.txt
coopr.data.cute.egg-info/top_level.txt
coopr/data/__init__.py
coopr/data/cute/__init__.py
coopr/data/cute/aircrfta.mod
coopr/data/cute/aircrfta.pyomo.nl
coopr/data/cute/aircrfta_cute.py
coopr/data/cute/aljazzaf.mod
coopr/data/cute/aljazzaf.pyomo.nl
coopr/data/cute/aljazzaf_cute.py
coopr/data/cute/artif.mod
coopr/data/cute/artif.pyomo.nl
coopr/data/cute/artif_cute.py
coopr/data/cute/arwhead.mod
coopr/data/cute/arwhead.pyomo.nl
coopr/data/cute/arwhead_cute.py
coopr/data/cute/avion2.mod
coopr/data/cute/avion2.pyomo.nl
coopr/data/cute/avion2_cute.py
coopr/data/cute/bard.dat
coopr/data/cute/bard.mod
coopr/data/cute/bard.pyomo.nl
coopr/data/cute/bard_cute.py
coopr/data/cute/bdqrtic.mod
coopr/data/cute/bdqrtic.pyomo.nl
coopr/data/cute/bdqrtic_cute.py
coopr/data/cute/biggs5.dat
coopr/data/cute/biggs5.mod
coopr/data/cute/biggs5.pyomo.nl
coopr/data/cute/biggs5_cute.py
coopr/data/cute/blockqp2.mod
coopr/data/cute/blockqp2.pyomo.nl
coopr/data/cute/blockqp2_cute.py
coopr/data/cute/booth.mod
coopr/data/cute/booth.pyomo.nl
coopr/data/cute/booth_cute.py
coopr/data/cute/bqp1var.mod
coopr/data/cute/bqp1var.pyomo.nl
coopr/data/cute/bqp1var_cute.py
coopr/data/cute/brownden.dat
coopr/data/cute/brownden.mod
coopr/data/cute/brownden.pyomo.nl
coopr/data/cute/brownden_cute.py
coopr/data/cute/bt1.dat
coopr/data/cute/bt1.mod
coopr/data/cute/bt1.pyomo.nl
coopr/data/cute/bt10.mod
coopr/data/cute/bt10.pyomo.nl
coopr/data/cute/bt10_cute.py
coopr/data/cute/bt13.dat
coopr/data/cute/bt13.mod
coopr/data/cute/bt13.pyomo.nl
coopr/data/cute/bt13_cute.py
coopr/data/cute/bt1_cute.py
coopr/data/cute/bt2.mod
coopr/data/cute/bt2.pyomo.nl
coopr/data/cute/bt2_cute.py
coopr/data/cute/bt3.mod
coopr/data/cute/bt3.pyomo.nl
coopr/data/cute/bt3_cute.py
coopr/data/cute/bt9.mod
coopr/data/cute/bt9.pyomo.nl
coopr/data/cute/bt9_cute.py
coopr/data/cute/byrdsphr.dat
coopr/data/cute/byrdsphr.mod
coopr/data/cute/byrdsphr.pyomo.nl
coopr/data/cute/byrdsphr_cute.py
